geneffect/__init__.py
geneffect/config.py
geneffect/default_config.py
geneffect/gene_data_loader.py
geneffect/reference_genome.py
geneffect/setup.py
geneffect/uniprot_and_pfam_data_loader.py
geneffect/util.py
geneffect/variant_processing.py
geneffect-1.2.4.dist-info/METADATA
geneffect-1.2.4.dist-info/WHEEL
geneffect-1.2.4.dist-info/top_level.txt
geneffect-1.2.4.dist-info/RECORD
