Metadata-Version: 2.1
Name: geneffect
Version: 1.2.4
Summary: A Python library for retrieving functional annotations of genes and analyzing the effects of genetic variants, currently focusing on proteomic data of protein-coding genes.
Home-page: https://github.com/nadavbra/geneffect
Author: Nadav Brandes
Author-email: nadav.brandes@mail.huji.ac.il
License: MIT
Platform: UNKNOWN
Requires-Dist: numpy
Requires-Dist: pandas
Requires-Dist: biopython
Requires-Dist: interval-tree
